loadax/__init__.py
loadax/batcher.py
loadax/py.typed
loadax/sharding_utilities.py
loadax/strategy.py
loadax/dataloader/__init__.py
loadax/dataloader/builder.py
loadax/dataloader/loader.py
loadax/dataloader/naive.py
loadax/dataloader/progress.py
loadax/dataloader/protocol.py
loadax/dataloader/sharding.py
loadax/dataset/__init__.py
loadax/dataset/in_memory.py
loadax/dataset/protocol.py
loadax/dataset/range.py
loadax/dataset/huggingface/__init__.py
loadax/dataset/huggingface/dataset.py
loadax/dataset/transform/__init__.py
loadax/dataset/transform/combined.py
loadax/dataset/transform/mapped.py
loadax/dataset/transform/partial.py
loadax/dataset/transform/sampled.py
loadax/dataset/transform/shuffled.py
loadax-0.2.1.dist-info/METADATA
loadax-0.2.1.dist-info/WHEEL
loadax-0.2.1.dist-info/licenses/LICENSE
loadax-0.2.1.dist-info/RECORD
