Metadata-Version: 2.3
Name: loadax
Version: 0.2.1
Summary: Dataloading for Jax
Author-email: Nick Wall <46641379+walln@users.noreply.github.com>
License: MIT License
License-File: LICENSE
Requires-Python: >=3.10
Requires-Dist: flax>=0.9.0
Requires-Dist: jax>=0.4.15
Requires-Dist: optax>=0.2.3
Provides-Extra: huggingface
Requires-Dist: datasets>=3.0.0; extra == 'huggingface'
Provides-Extra: polars
Requires-Dist: polars>=1.7.1; extra == 'polars'
